mooquant_formula/__init__.py
mooquant_formula/cli.py
mooquant_formula/settings.py
mooquant_formula/formula/__init__.py
mooquant_formula/formula/extend.py
mooquant_formula/formula/standard.py
mooquant_formula/helpers/__init__.py
mooquant_formula/helpers/holiday.py
mooquant_formula/helpers/symbol.py
mooquant_formula-0.1.2.dist-info/DESCRIPTION.rst
mooquant_formula-0.1.2.dist-info/METADATA
mooquant_formula-0.1.2.dist-info/RECORD
mooquant_formula-0.1.2.dist-info/WHEEL
mooquant_formula-0.1.2.dist-info/entry_points.txt
mooquant_formula-0.1.2.dist-info/metadata.json
mooquant_formula-0.1.2.dist-info/top_level.txt
